nonebot_plugin_lazytea_shell_extension/__call__.py
nonebot_plugin_lazytea_shell_extension/__init__.py
nonebot_plugin_lazytea_shell_extension/__ui__.py
nonebot_plugin_lazytea_shell_extension/config.py
nonebot_plugin_lazytea_shell_extension-0.0.1.post1.dist-info/METADATA
nonebot_plugin_lazytea_shell_extension-0.0.1.post1.dist-info/WHEEL
nonebot_plugin_lazytea_shell_extension-0.0.1.post1.dist-info/top_level.txt
nonebot_plugin_lazytea_shell_extension-0.0.1.post1.dist-info/RECORD
