Metadata-Version: 2.4
Name: nonebot_plugin_lazytea_shell_extension
Version: 0.0.1.post1
Summary: NoneBot2 lazytea的命令扩展, 允许指令操作GUI
Requires-Python: >=3.10
Requires-Dist: nonebot-plugin-alconna>=0.59.0
Requires-Dist: nonebot-plugin-lazytea>=0.0.2
Requires-Dist: nonebot2>=2.4.2
